{
  "alpaca": {
    "startDate": "2026-06-01",
    "startBalance": 2340.62,
    "trades": [
      {
        "date": "2026-06-01",
        "ticker": "FCX",
        "direction": "put",
        "contracts": 1,
        "entry": 1.86,
        "exit": 1.32,
        "holdMin": 57,
        "pnlUsd": -54.12,
        "pnlPct": -29.0,
        "fees": 0.12,
        "strategy": "v-reversal"
      },
      {
        "date": "2026-06-02",
        "ticker": "FCX",
        "direction": "put",
        "contracts": 2,
        "entry": 2.11,
        "exit": 1.54,
        "holdMin": 37,
        "pnlUsd": -114.1,
        "pnlPct": -27.0,
        "fees": 0.24,
        "strategy": "v-reversal"
      }
    ]
  },
  "robinhood": {
    "startDate": "2026-06-01",
    "startBalance": 40.0,
    "trades": [],
    "openPositions": [
      {
        "ticker": "UNCY",
        "shares": 5,
        "costBasis": 7.46,
        "currentPrice": 7.71,
        "openDate": "2026-06-01"
      }
    ],
    "equityHistory": [
      {
        "date": "2026-06-01",
        "equity": 40.0
      },
      {
        "date": "2026-06-02",
        "equity": 39.8
      },
      {
        "date": "2026-06-03",
        "equity": 39.9
      },
      {
        "date": "2026-06-04",
        "equity": 40.3
      },
      {
        "date": "2026-06-05",
        "equity": 37.3
      },
      {
        "date": "2026-06-08",
        "equity": 36.0
      },
      {
        "date": "2026-06-09",
        "equity": 39.0
      },
      {
        "date": "2026-06-10",
        "equity": 41.25
      }
    ]
  },
  "paperB125": {
    "startDate": "2026-05-08",
    "startBalance": 10000.0,
    "trades": [],
    "openPositions": [
      {
        "ticker": "NVDA",
        "optionSym": "NVDA260612C00220000",
        "contracts": 1,
        "entryDate": "2026-05-11",
        "entry": 12.955,
        "expiry": "2026-06-12",
        "costBasis": 1295.5
      },
      {
        "ticker": "META",
        "optionSym": "META260612C00600000",
        "contracts": 1,
        "entryDate": "2026-05-11",
        "entry": 24.55,
        "expiry": "2026-06-12",
        "costBasis": 2455.0
      }
    ],
    "equityHistory": [
      {
        "date": "2026-05-08",
        "equity": 10000.0
      },
      {
        "date": "2026-05-11",
        "equity": 9982.35
      },
      {
        "date": "2026-05-12",
        "equity": 9554.35
      },
      {
        "date": "2026-05-14",
        "equity": 11944.85
      },
      {
        "date": "2026-05-15",
        "equity": 11001.85
      },
      {
        "date": "2026-05-18",
        "equity": 10170.85
      },
      {
        "date": "2026-05-19",
        "equity": 9786.85
      },
      {
        "date": "2026-05-20",
        "equity": 9773.35
      },
      {
        "date": "2026-05-21",
        "equity": 9096.35
      },
      {
        "date": "2026-05-22",
        "equity": 9056.35
      },
      {
        "date": "2026-05-25",
        "equity": 9149.85
      },
      {
        "date": "2026-05-26",
        "equity": 8949.85
      },
      {
        "date": "2026-05-27",
        "equity": 8908.85
      },
      {
        "date": "2026-05-28",
        "equity": 10228.85
      },
      {
        "date": "2026-05-29",
        "equity": 9835.35
      },
      {
        "date": "2026-06-01",
        "equity": 9258.85
      },
      {
        "date": "2026-06-02",
        "equity": 9001.35
      },
      {
        "date": "2026-06-03",
        "equity": 9274.35
      },
      {
        "date": "2026-06-04",
        "equity": 9891.35
      }
    ]
  },
  "orbV21Paper": {
    "startDate": "2026-06-05",
    "startBalance": 10000.0,
    "trades": [],
    "openPositions": [],
    "equityHistory": [
      {
        "date": "2026-06-05",
        "equity": 99659.89
      },
      {
        "date": "2026-06-08",
        "equity": 99659.89
      },
      {
        "date": "2026-06-09",
        "equity": 99659.89
      },
      {
        "date": "2026-06-10",
        "equity": 99659.89
      }
    ]
  }
}
